odoo10_addon_oca_custom-10.0.1.0.0-nspkg.pth
odoo/addons/oca_custom/README.rst
odoo/addons/oca_custom/__init__.py
odoo/addons/oca_custom/__manifest__.py
odoo/addons/oca_custom/models/__init__.py
odoo/addons/oca_custom/models/res_partner.py
odoo/addons/oca_custom/static/description/icon.png
odoo/addons/oca_custom/views/res_partner.xml
odoo10_addon_oca_custom-10.0.1.0.0.dist-info/METADATA
odoo10_addon_oca_custom-10.0.1.0.0.dist-info/WHEEL
odoo10_addon_oca_custom-10.0.1.0.0.dist-info/namespace_packages.txt
odoo10_addon_oca_custom-10.0.1.0.0.dist-info/top_level.txt
odoo10_addon_oca_custom-10.0.1.0.0.dist-info/RECORD
